[{
		"date": "2017-07-18T19:00:59Z",
		"name": "Pete",
		"comment": "My comment",
		"amount": 6.25,
		"currency": "USD"
	},
	{
		"date": "2017-05-18T19:00:59Z",
		"name": "Karl",
		"comment": "Karl's comment",
		"amount": 50,
		"currency": "CAD"
	},
	{
		"date": "2017-05-18T19:00:59Z",
		"name": "Karl",
		"comment": "Karl's comment",
		"amount": 50,
		"currency": "CAD"
	},
	{
		"date": "2017-05-18T19:00:59Z",
		"name": "Karl",
		"comment": "Karl's comment",
		"amount": 50,
		"currency": "CAD"
	},
	{
		"date": "2017-05-18T19:00:59Z",
		"name": "Karl",
		"comment": "Karl's comment",
		"amount": 50,
		"currency": "CAD"
	},
	{
		"date": "2017-05-18T19:00:59Z",
		"name": "Karl",
		"comment": "Karl's comment",
		"amount": 50,
		"currency": "CAD"
	},
	{
		"date": "2017-05-18T19:00:59Z",
		"name": "Karl",
		"comment": "Karl's comment",
		"amount": 50,
		"currency": "CAD"
	},
	{
		"date": "2017-05-18T19:00:59Z",
		"name": "Karl",
		"comment": "Karl's comment",
		"amount": 50,
		"currency": "CAD"
	},
	{
		"date": "2017-05-18T19:00:59Z",
		"name": "Karl",
		"comment": "Karl's comment",
		"amount": 50,
		"currency": "CAD"
	},
	{
		"date": "2017-05-18T19:00:59Z",
		"name": "Karl",
		"comment": "Karl's comment",
		"amount": 50,
		"currency": "CAD"
	},
	{
		"date": "2017-05-18T19:00:59Z",
		"name": "Karl",
		"comment": "Karl's comment",
		"amount": 50,
		"currency": "CAD"
	}
]